{"chanID":"-1001065120307","lastUpdated":"2016-12-03T22:46:22Z","total":[{"playerID":"298381661","name":"Nadiva S","score":2674,"position":1},{"playerID":"270026202","name":"Laras","score":2143,"position":2},{"playerID":"220914120","name":"Adi Nugroho Lingga","score":1074,"position":3},{"playerID":"276136803","name":"Andi Mahathir","score":880,"position":4},{"playerID":"298520456","name":"Fattah","score":879,"position":5},{"playerID":"294835799","name":"Deswita","score":778,"position":6},{"playerID":"274762992","name":"Arjun R","score":737,"position":7},{"playerID":"205558587","name":"Gregorius Ardhya","score":538,"position":8},{"playerID":"229382997","name":"Alwan Adiyasa","score":381,"position":9},{"playerID":"288258997","name":"Risya Hadiansyah","score":363,"position":10},{"playerID":"296600139","name":"Iqbale Alfian","score":193,"position":11},{"playerID":"229589761","name":"Donny Bawataa","score":193,"position":12},{"playerID":"210552797","name":"Hernan Crespo","score":100,"position":13},{"playerID":"259618600","name":"Leonardo Octavianus","score":73,"position":14},{"playerID":"290811176","name":"Khairi Auladi","score":60,"position":15},{"playerID":"278421227","name":"Ridha","score":16,"position":16},{"playerID":"233539290","name":"Dimasrh Sadewa","score":3,"position":17}],"rank":{"2016-48":[{"playerID":"298381661","name":"Nadiva S","score":2674,"position":1},{"playerID":"270026202","name":"Laras","score":2143,"position":2},{"playerID":"220914120","name":"Adi Nugroho Lingga","score":1074,"position":3},{"playerID":"276136803","name":"Andi Mahathir","score":880,"position":4},{"playerID":"298520456","name":"Fattah","score":879,"position":5},{"playerID":"294835799","name":"Deswita","score":778,"position":6},{"playerID":"274762992","name":"Arjun R","score":737,"position":7},{"playerID":"205558587","name":"Gregorius Ardhya","score":538,"position":8},{"playerID":"229382997","name":"Alwan Adiyasa","score":381,"position":9},{"playerID":"288258997","name":"Risya Hadiansyah","score":363,"position":10},{"playerID":"296600139","name":"Iqbale Alfian","score":193,"position":11},{"playerID":"229589761","name":"Donny Bawataa","score":193,"position":12},{"playerID":"210552797","name":"Hernan Crespo","score":100,"position":13},{"playerID":"259618600","name":"Leonardo Octavianus","score":73,"position":14},{"playerID":"290811176","name":"Khairi Auladi","score":60,"position":15},{"playerID":"278421227","name":"Ridha","score":16,"position":16},{"playerID":"233539290","name":"Dimasrh Sadewa","score":3,"position":17}]}}
