{"chanID":"-1001076441639","lastUpdated":"2016-12-16T05:00:08Z","total":[{"playerID":"207995912","name":"Joscelind Setiawan","score":239,"position":1},{"playerID":"222093398","name":"Michelle Aurellia","score":178,"position":2},{"playerID":"234173799","name":"Zaenal Suram","score":47,"position":3}],"rank":{"2016-50":[{"playerID":"207995912","name":"Joscelind Setiawan","score":239,"position":1},{"playerID":"222093398","name":"Michelle Aurellia","score":178,"position":2},{"playerID":"234173799","name":"Zaenal Suram","score":47,"position":3}]}}
