{"chanID":"-1001050395545","lastUpdated":"2016-12-03T22:46:22Z","total":[{"playerID":"251125252","name":"Eveline。","score":174,"position":1},{"playerID":"214756438","name":"troye sivan~","score":163,"position":2},{"playerID":"252207602","name":"Martha Christina Tiahahu/opy","score":106,"position":3},{"playerID":"221974248","name":"Cut Nyak Meutia Moci","score":96,"position":4},{"playerID":"55599427","name":"Chandra Nugraha (Ube)","score":7,"position":5},{"playerID":"134861649","name":"R.A Kartini 🐰 Yes","score":3,"position":6}],"rank":{"2016-48":[{"playerID":"251125252","name":"Eveline。","score":174,"position":1},{"playerID":"214756438","name":"troye sivan~","score":163,"position":2},{"playerID":"252207602","name":"Martha Christina Tiahahu/opy","score":106,"position":3},{"playerID":"221974248","name":"Cut Nyak Meutia Moci","score":96,"position":4},{"playerID":"55599427","name":"Chandra Nugraha (Ube)","score":7,"position":5},{"playerID":"134861649","name":"R.A Kartini 🐰 Yes","score":3,"position":6}]}}
