{"chanID":"-110907217","lastUpdated":"2016-11-30T05:00:14+01:00","total":[{"playerID":"225147918","name":"Nissah GF","score":15108,"position":1},{"playerID":"192353385","name":"Hna madaMe","score":8412,"position":2},{"playerID":"222867475","name":"Hafiza Dhyantry Ramadhini","score":8001,"position":3},{"playerID":"254279880","name":"Shu Lu Han","score":4276,"position":4},{"playerID":"240998944","name":"madaMe HanHan","score":2439,"position":5},{"playerID":"249210201","name":"Ghina Almira","score":1582,"position":6},{"playerID":"220786453","name":"madaMe ipon","score":1276,"position":7}],"rank":{"2016-27":[{"playerID":"192353385","name":"Hna madaMe","score":2560,"position":1},{"playerID":"225147918","name":"Nissah GF","score":2190,"position":2},{"playerID":"222867475","name":"Hafiza Dhyantry Ramadhini","score":1420,"position":3},{"playerID":"254279880","name":"Jo Jo","score":1237,"position":4},{"playerID":"240998944","name":"madaMe HanHan","score":379,"position":5},{"playerID":"249210201","name":"Ghina Almira","score":164,"position":6}],"2016-28":[{"playerID":"225147918","name":"Nissah GF","score":5438,"position":1},{"playerID":"192353385","name":"Hna madaMe","score":2421,"position":2},{"playerID":"222867475","name":"Hafiza Dhyantry Ramadhini","score":1464,"position":3},{"playerID":"254279880","name":"Jo Jo","score":1447,"position":4},{"playerID":"240998944","name":"madaMe HanHan","score":885,"position":5},{"playerID":"249210201","name":"Ghina Almira","score":709,"position":6}],"2016-29":[{"playerID":"225147918","name":"Nissah GF","score":5924,"position":1},{"playerID":"192353385","name":"Hna madaMe","score":3077,"position":2},{"playerID":"222867475","name":"Hafiza Dhyantry Ramadhini","score":3013,"position":3},{"playerID":"254279880","name":"Jo Jo","score":1447,"position":4},{"playerID":"240998944","name":"madaMe HanHan","score":1175,"position":5},{"playerID":"249210201","name":"Ghina Almira","score":709,"position":6}],"2016-47":[{"playerID":"222867475","name":"Hafiza Dhyantry Ramadhini","score":951,"position":1},{"playerID":"225147918","name":"Nissah GF","score":778,"position":2},{"playerID":"220786453","name":"madaMe ipon","score":525,"position":3},{"playerID":"192353385","name":"Hna madaMe","score":177,"position":4},{"playerID":"254279880","name":"Shu Lu Han","score":62,"position":5}],"2016-48":[{"playerID":"222867475","name":"Hafiza Dhyantry Ramadhini","score":1153,"position":1},{"playerID":"225147918","name":"Nissah GF","score":778,"position":2},{"playerID":"220786453","name":"madaMe ipon","score":751,"position":3},{"playerID":"192353385","name":"Hna madaMe","score":177,"position":4},{"playerID":"254279880","name":"Shu Lu Han","score":83,"position":5}]}}
