{"chanID":"-132849886","lastUpdated":"2016-12-03T22:46:22Z","total":[{"playerID":"262563660","name":"Johny Depp","score":6766,"position":1},{"playerID":"276558714","name":"Aminatus","score":5442,"position":2},{"playerID":"293273951","name":"I worship dragon","score":5160,"position":3},{"playerID":"255213272","name":"Ragil Satrio","score":4552,"position":4},{"playerID":"262675368","name":"Danang Aprias","score":3590,"position":5},{"playerID":"286564237","name":"Putri Kuspuji","score":2038,"position":6},{"playerID":"256850927","name":"Aldo Albilase","score":1007,"position":7},{"playerID":"225590313","name":"Diaz Hanin","score":781,"position":8},{"playerID":"320991412","name":"Sekar Palupi","score":97,"position":9}],"rank":{"2016-48":[{"playerID":"262563660","name":"Johny Depp","score":6766,"position":1},{"playerID":"276558714","name":"Aminatus","score":5442,"position":2},{"playerID":"293273951","name":"I worship dragon","score":5160,"position":3},{"playerID":"255213272","name":"Ragil Satrio","score":4552,"position":4},{"playerID":"262675368","name":"Danang Aprias","score":3590,"position":5},{"playerID":"286564237","name":"Putri Kuspuji","score":2038,"position":6},{"playerID":"256850927","name":"Aldo Albilase","score":1007,"position":7},{"playerID":"225590313","name":"Diaz Hanin","score":781,"position":8},{"playerID":"320991412","name":"Sekar Palupi","score":97,"position":9}]}}
