{"chanID":"-134473864","lastUpdated":"2016-12-03T22:46:22Z","total":[{"playerID":"287432382","name":"Alvi Andrianto","score":143,"position":1},{"playerID":"280064363","name":"Lingga","score":94,"position":2},{"playerID":"128858500","name":"Adrian","score":60,"position":3}],"rank":{"2016-48":[{"playerID":"287432382","name":"Alvi Andrianto","score":143,"position":1},{"playerID":"280064363","name":"Lingga","score":94,"position":2},{"playerID":"128858500","name":"Adrian","score":60,"position":3}]}}
