{"chanID":"-141841845","lastUpdated":"2016-12-14T05:00:11Z","total":[{"playerID":"283731909","name":"Kleine Stier","score":1388,"position":1},{"playerID":"273961795","name":"hello kitty","score":920,"position":2},{"playerID":"316064505","name":"Indah Zulma","score":379,"position":3},{"playerID":"270058862","name":"Desi andria","score":317,"position":4},{"playerID":"302814365","name":"Navariz Ariando Musri","score":171,"position":5},{"playerID":"304829383","name":"Vika Fadhillah","score":167,"position":6},{"playerID":"306095460","name":"Citra triana","score":108,"position":7},{"playerID":"309404644","name":"fairuz","score":42,"position":8}],"rank":{"2016-48":[{"playerID":"273961795","name":"Shofi Afifah","score":414,"position":1},{"playerID":"316064505","name":"Indah Zulma","score":379,"position":2},{"playerID":"283731909","name":"Adhieneo Al-azhany","score":196,"position":3},{"playerID":"304829383","name":"Vika Fadhillah","score":167,"position":4},{"playerID":"270058862","name":"Desi Andria","score":55,"position":5},{"playerID":"302814365","name":"Navariz Ariando","score":17,"position":6},{"playerID":"306095460","name":"Citra triana","score":6,"position":7}],"2016-49":[{"playerID":"283731909","name":"Kleine Stier","score":596,"position":1},{"playerID":"273961795","name":"hello kitty","score":253,"position":2},{"playerID":"270058862","name":"Desi Andria","score":131,"position":3},{"playerID":"302814365","name":"Navariz Ariando","score":77,"position":4},{"playerID":"306095460","name":"Citra triana","score":51,"position":5},{"playerID":"309404644","name":"Fairuz Salsabila","score":21,"position":6}],"2016-50":[{"playerID":"283731909","name":"Kleine Stier","score":596,"position":1},{"playerID":"273961795","name":"hello kitty","score":253,"position":2},{"playerID":"270058862","name":"Desi andria","score":131,"position":3},{"playerID":"302814365","name":"Navariz Ariando Musri","score":77,"position":4},{"playerID":"306095460","name":"Citra triana","score":51,"position":5},{"playerID":"309404644","name":"fairuz","score":21,"position":6}]}}
