{"chanID":"-143571308","lastUpdated":"2016-12-10T05:00:08Z","total":[{"playerID":"209656481","name":"Rafika Fitri","score":95,"position":1},{"playerID":"269994614","name":"Diana Emeilia","score":81,"position":2},{"playerID":"324489292","name":"Riku Ci","score":33,"position":3},{"playerID":"260272025","name":"Dias Rahmandini","score":26,"position":4},{"playerID":"181959821","name":"qorry aina","score":24,"position":5}],"rank":{"2016-49":[{"playerID":"209656481","name":"Rafika Fitri","score":95,"position":1},{"playerID":"269994614","name":"Diana Emeilia","score":81,"position":2},{"playerID":"324489292","name":"Riku Ci","score":33,"position":3},{"playerID":"260272025","name":"Dias Rahmandini","score":26,"position":4},{"playerID":"181959821","name":"qorry aina","score":24,"position":5}]}}
