{"chanID":"-150103109","lastUpdated":"2016-11-27T05:00:11+01:00","total":[{"playerID":"183803428","name":"Ayu","score":1591,"position":1},{"playerID":"177586164","name":"Rio Hadmojo","score":850,"position":2},{"playerID":"153149207","name":"Deni Arifin","score":726,"position":3},{"playerID":"231845827","name":"Astrina Majid","score":568,"position":4},{"playerID":"163680158","name":"Diana Rahmawati","score":544,"position":5},{"playerID":"166220108","name":"Ion Bagas Prakoso","score":469,"position":6},{"playerID":"215559352","name":"Suci Karnia Ramadhan","score":339,"position":7},{"playerID":"170509358","name":"Dicky Pratama","score":294,"position":8},{"playerID":"167229193","name":"Puput (Fatonah Dwi P)","score":30,"position":9},{"playerID":"153120859","name":"Nuryani Elisoni","score":18,"position":10}],"rank":{"2016-47":[{"playerID":"183803428","name":"Ayu","score":1591,"position":1},{"playerID":"177586164","name":"Rio Hadmojo","score":850,"position":2},{"playerID":"153149207","name":"Deni Arifin","score":726,"position":3},{"playerID":"231845827","name":"Astrina Majid","score":568,"position":4},{"playerID":"163680158","name":"Diana Rahmawati","score":544,"position":5},{"playerID":"166220108","name":"Ion Bagas Prakoso","score":469,"position":6},{"playerID":"215559352","name":"Suci Karnia Ramadhan","score":339,"position":7},{"playerID":"170509358","name":"Dicky Pratama","score":294,"position":8},{"playerID":"167229193","name":"Puput (Fatonah Dwi P)","score":30,"position":9},{"playerID":"153120859","name":"Nuryani Elisoni","score":18,"position":10}]}}
