{"chanID":"-152307205","lastUpdated":"2016-12-24T05:00:08Z","total":[{"playerID":"300614366","name":"Nelva Meldyta","score":4658,"position":1},{"playerID":"284601468","name":"Meldyviano Alvinzky","score":2145,"position":2},{"playerID":"311711665","name":"Meldy","score":1444,"position":3},{"playerID":"319544675","name":"Alant","score":842,"position":4},{"playerID":"328686413","name":"Johnny","score":575,"position":5}],"rank":{"2016-48":[{"playerID":"300614366","name":"Nelva Meldyta","score":1038,"position":1},{"playerID":"328686413","name":"Johnny","score":396,"position":2},{"playerID":"284601468","name":"Meldyviano Alvinzky","score":247,"position":3},{"playerID":"311711665","name":"Meldy","score":188,"position":4}],"2016-50":[{"playerID":"328686413","name":"Johnny","score":123,"position":1},{"playerID":"311711665","name":"Meldy","score":73,"position":2},{"playerID":"284601468","name":"Meldyviano Alvinzky","score":2,"position":3}],"2016-51":[{"playerID":"300614366","name":"Nelva Meldyta","score":3620,"position":1},{"playerID":"284601468","name":"Meldyviano Alvinzky","score":1896,"position":2},{"playerID":"311711665","name":"Meldy","score":1183,"position":3},{"playerID":"319544675","name":"Alant","score":842,"position":4},{"playerID":"328686413","name":"Johnny","score":56,"position":5}]}}
