{"chanID":"-152802159","lastUpdated":"2016-12-27T05:00:11Z","total":[{"playerID":"283631537","name":"Erni Nuribachri","score":16095,"position":1},{"playerID":"295990035","name":"Faisal Bachri","score":14159,"position":2},{"playerID":"257198556","name":"Rini Appiyani","score":8390,"position":3},{"playerID":"297065673","name":"bejo mas","score":6342,"position":4},{"playerID":"271633346","name":"Putri Potter","score":4678,"position":5},{"playerID":"298806606","name":"rizky septian hardi","score":4327,"position":6},{"playerID":"300543924","name":"MiarshaTomy","score":4325,"position":7},{"playerID":"237142272","name":"Sri Wahyuni","score":2613,"position":8},{"playerID":"290186302","name":"wan ti","score":1448,"position":9},{"playerID":"271137995","name":"TWB","score":474,"position":10},{"playerID":"275763911","name":"Agus Mustofa","score":50,"position":11},{"playerID":"226344453","name":"41820 Lissepty","score":16,"position":12}],"rank":{"2016-48":[{"playerID":"271633346","name":"Putri Potter","score":382,"position":1},{"playerID":"271137995","name":"TWB","score":371,"position":2},{"playerID":"298806606","name":"rizky septian hardi","score":304,"position":3},{"playerID":"290186302","name":"wan ti","score":216,"position":4},{"playerID":"297065673","name":"bejo mas","score":96,"position":5},{"playerID":"226344453","name":"41820 Lissepty","score":16,"position":6}],"2016-49":[{"playerID":"283631537","name":"Erni Nuribachri","score":259,"position":1},{"playerID":"271633346","name":"Putri Potter","score":248,"position":2},{"playerID":"297065673","name":"bejo mas","score":193,"position":3},{"playerID":"290186302","name":"wan ti","score":167,"position":4},{"playerID":"237142272","name":"Sri Wahyuni","score":97,"position":5},{"playerID":"271137995","name":"TWB","score":23,"position":6}],"2016-50":[{"playerID":"283631537","name":"Erni Nuribachri","score":2379,"position":1},{"playerID":"297065673","name":"bejo mas","score":1051,"position":2},{"playerID":"295990035","name":"Faisal Bachri","score":989,"position":3},{"playerID":"237142272","name":"Sri Wahyuni","score":650,"position":4},{"playerID":"257198556","name":"Rini Appiyani","score":566,"position":5},{"playerID":"290186302","name":"wan ti","score":431,"position":6},{"playerID":"271633346","name":"Putri Potter","score":248,"position":7},{"playerID":"271137995","name":"TWB","score":44,"position":8}],"2016-51":[{"playerID":"283631537","name":"Erni Nuribachri","score":6416,"position":1},{"playerID":"295990035","name":"Faisal Bachri","score":6225,"position":2},{"playerID":"257198556","name":"Rini Appiyani","score":3405,"position":3},{"playerID":"297065673","name":"bejo mas","score":2024,"position":4},{"playerID":"300543924","name":"MiarshaTomy","score":2018,"position":5},{"playerID":"298806606","name":"rizky septian hardi","score":1770,"position":6},{"playerID":"271633346","name":"Putri Potter","score":1402,"position":7},{"playerID":"237142272","name":"Sri Wahyuni","score":815,"position":8},{"playerID":"290186302","name":"wan ti","score":317,"position":9},{"playerID":"275763911","name":"Agus Mustofa","score":25,"position":10},{"playerID":"271137995","name":"TWB","score":18,"position":11}],"2016-52":[{"playerID":"283631537","name":"Erni Nuribachri","score":7041,"position":1},{"playerID":"295990035","name":"Faisal Bachri","score":6945,"position":2},{"playerID":"257198556","name":"Rini Appiyani","score":4419,"position":3},{"playerID":"297065673","name":"bejo mas","score":2978,"position":4},{"playerID":"271633346","name":"Putri Potter","score":2398,"position":5},{"playerID":"300543924","name":"MiarshaTomy","score":2307,"position":6},{"playerID":"298806606","name":"rizky septian hardi","score":2253,"position":7},{"playerID":"237142272","name":"Sri Wahyuni","score":1051,"position":8},{"playerID":"290186302","name":"wan ti","score":317,"position":9},{"playerID":"275763911","name":"Agus Mustofa","score":25,"position":10},{"playerID":"271137995","name":"TWB","score":18,"position":11}]}}
