{"chanID":"-152480104","lastUpdated":"2016-12-22T05:00:09Z","total":[{"playerID":"283884530","name":"Kadal Metal","score":2203,"position":1},{"playerID":"305177877","name":"EAC","score":551,"position":2},{"playerID":"310459981","name":"Anisya Ahladita","score":348,"position":3},{"playerID":"316584522","name":"Vnd Viandi","score":315,"position":4}],"rank":{"2016-51":[{"playerID":"283884530","name":"Kadal Metal","score":2203,"position":1},{"playerID":"305177877","name":"EAC","score":551,"position":2},{"playerID":"310459981","name":"Anisya Ahladita","score":348,"position":3},{"playerID":"316584522","name":"Vnd Viandi","score":315,"position":4}]}}
