{"chanID":"-153898313","lastUpdated":"2017-01-01T23:55:11Z","total":[{"playerID":"312400933","name":"Prilly","score":1091,"position":1},{"playerID":"327051612","name":"Fatih Nk","score":580,"position":2},{"playerID":"306317511","name":"Nur'aini Pharadisa","score":311,"position":3},{"playerID":"298366930","name":"Rendy Oktafian","score":207,"position":4},{"playerID":"302743301","name":"Septiantika Cahyaditami","score":157,"position":5},{"playerID":"322856479","name":"Dimas Taufik","score":73,"position":6}],"rank":{"2016-52":[{"playerID":"312400933","name":"Prilly","score":1091,"position":1},{"playerID":"327051612","name":"Fatih Nk","score":580,"position":2},{"playerID":"306317511","name":"Nur'aini Pharadisa","score":311,"position":3},{"playerID":"298366930","name":"Rendy Oktafian","score":207,"position":4},{"playerID":"302743301","name":"Septiantika Cahyaditami","score":157,"position":5},{"playerID":"322856479","name":"Dimas Taufik","score":73,"position":6}]}}
