{"chanID":"-153407728","lastUpdated":"2016-12-03T22:46:22Z","total":[{"playerID":"296824705","name":"Nurul Aini","score":5694,"position":1},{"playerID":"260751870","name":"Nurul Fitriani","score":4912,"position":2},{"playerID":"247438336","name":"Fidia Wijaya","score":2417,"position":3},{"playerID":"293814321","name":"Riffani Muslimawati","score":2345,"position":4},{"playerID":"260561188","name":"Sumiarsih 0mie","score":2082,"position":5},{"playerID":"217257725","name":"adi firmansyah","score":1727,"position":6},{"playerID":"286177003","name":"Ikhwan Ghazali","score":1649,"position":7},{"playerID":"250108320","name":"Muhamad Taufiq","score":357,"position":8}],"rank":{"2016-48":[{"playerID":"296824705","name":"Nurul Aini","score":5694,"position":1},{"playerID":"260751870","name":"Nurul Fitriani","score":4912,"position":2},{"playerID":"247438336","name":"Fidia Wijaya","score":2417,"position":3},{"playerID":"293814321","name":"Riffani Muslimawati","score":2345,"position":4},{"playerID":"260561188","name":"Sumiarsih 0mie","score":2082,"position":5},{"playerID":"217257725","name":"adi firmansyah","score":1727,"position":6},{"playerID":"286177003","name":"Ikhwan Ghazali","score":1649,"position":7},{"playerID":"250108320","name":"Muhamad Taufiq","score":357,"position":8}]}}
