{"chanID":"-154168998","lastUpdated":"2016-12-02T05:00:14+01:00","total":[{"playerID":"291368482","name":"Revin Vieri","score":518,"position":1},{"playerID":"262276344","name":"Leon Sanjaya","score":206,"position":2},{"playerID":"297468989","name":"Kikies Surya","score":188,"position":3},{"playerID":"236442679","name":"Cindy Hermawan","score":186,"position":4}],"rank":{"2016-47":[{"playerID":"291368482","name":"Revin Vieri","score":259,"position":1},{"playerID":"262276344","name":"Leon Sanjaya","score":103,"position":2},{"playerID":"297468989","name":"Kikies Surya","score":94,"position":3},{"playerID":"236442679","name":"Cindy Hermawan","score":93,"position":4}],"2016-48":[{"playerID":"291368482","name":"Revin Vieri","score":259,"position":1},{"playerID":"262276344","name":"Leon Sanjaya","score":103,"position":2},{"playerID":"297468989","name":"Kikies Surya","score":94,"position":3},{"playerID":"236442679","name":"Cindy Hermawan","score":93,"position":4}]}}
