{"chanID":"-156733714","lastUpdated":"2016-12-06T05:00:08Z","total":[{"playerID":"328462267","name":"Maulana Yusuf Abdullah","score":1015,"position":1},{"playerID":"295854849","name":"Steven Afandy","score":1004,"position":2},{"playerID":"246372472","name":"Yafet Agustinus","score":766,"position":3},{"playerID":"282595782","name":"Ricky Dermawan A","score":457,"position":4},{"playerID":"303971090","name":"Nicholas Agung Setiawan","score":179,"position":5},{"playerID":"324163882","name":"Riyanti Teresa Tedja","score":70,"position":6}],"rank":{"2016-49":[{"playerID":"328462267","name":"Maulana Yusuf Abdullah","score":1015,"position":1},{"playerID":"295854849","name":"Steven Afandy","score":1004,"position":2},{"playerID":"246372472","name":"Yafet Agustinus","score":766,"position":3},{"playerID":"282595782","name":"Ricky Dermawan A","score":457,"position":4},{"playerID":"303971090","name":"Nicholas Agung Setiawan","score":179,"position":5},{"playerID":"324163882","name":"Riyanti Teresa Tedja","score":70,"position":6}]}}
