{"chanID":"-157969128","lastUpdated":"2016-12-03T22:46:22Z","total":[{"playerID":"204227502","name":"Rizky Baby","score":768,"position":1},{"playerID":"251553876","name":"Bintang Gemilang","score":621,"position":2},{"playerID":"243941563","name":"Adam Irfan Hawari","score":420,"position":3}],"rank":{"2016-48":[{"playerID":"204227502","name":"Rizky Baby","score":768,"position":1},{"playerID":"251553876","name":"Bintang Gemilang","score":621,"position":2},{"playerID":"243941563","name":"Adam Irfan Hawari","score":420,"position":3}]}}
