{"chanID":"-161240543","lastUpdated":"2016-12-03T22:46:22Z","total":[{"playerID":"189066096","name":"Selly Octavia","score":466,"position":1},{"playerID":"229755417","name":"Deska Aulia","score":433,"position":2},{"playerID":"185006524","name":"Widyanti","score":401,"position":3},{"playerID":"172673297","name":"Dhea Hendri","score":280,"position":4},{"playerID":"260597265","name":"Tri Handayani","score":169,"position":5},{"playerID":"248833561","name":"Iptu Nurani","score":116,"position":6},{"playerID":"223861673","name":"catur kurniawati","score":79,"position":7},{"playerID":"243695969","name":"Intan Ayu Iqlima","score":51,"position":8},{"playerID":"286150364","name":"Umi Andini Putri","score":17,"position":9}],"rank":{"2016-42":[{"playerID":"189066096","name":"Selly Octavia","score":323,"position":1},{"playerID":"185006524","name":"Widyanti","score":282,"position":2},{"playerID":"172673297","name":"Dhea Hendri","score":191,"position":3},{"playerID":"248833561","name":"Iptu Nurani","score":99,"position":4},{"playerID":"260597265","name":"Tri Handayani","score":92,"position":5},{"playerID":"223861673","name":"catur kurniawati","score":79,"position":6},{"playerID":"229755417","name":"Deska Aulia","score":63,"position":7},{"playerID":"243695969","name":"Intan Ayu Iqlima","score":51,"position":8},{"playerID":"286150364","name":"Umi Andini Putri","score":17,"position":9}],"2016-48":[{"playerID":"229755417","name":"Deska Aulia","score":370,"position":1},{"playerID":"189066096","name":"Selly Octavia","score":143,"position":2},{"playerID":"185006524","name":"Widyanti","score":119,"position":3},{"playerID":"172673297","name":"Dhea Hendri","score":89,"position":4},{"playerID":"260597265","name":"Tri Handayani","score":77,"position":5},{"playerID":"248833561","name":"Iptu Nurani","score":17,"position":6}]}}
