{"chanID":"-166301291","lastUpdated":"2016-12-03T22:46:22Z","total":[{"playerID":"190249604","name":"Sanji","score":173,"position":1},{"playerID":"201722443","name":"Chaii~chai","score":166,"position":2},{"playerID":"254252454","name":"Muhammad Rizali N","score":33,"position":3}],"rank":{"2016-48":[{"playerID":"190249604","name":"Sanji","score":173,"position":1},{"playerID":"201722443","name":"Chaii~chai","score":166,"position":2},{"playerID":"254252454","name":"Muhammad Rizali N","score":33,"position":3}]}}
