{"chanID":"-166701834","lastUpdated":"2016-12-03T22:46:22Z","total":[{"playerID":"276413484","name":"Astri Winati","score":540,"position":1},{"playerID":"259002958","name":"Iklas SIG","score":351,"position":2},{"playerID":"269902468","name":"Nimah Eka Winati","score":348,"position":3},{"playerID":"192239640","name":"Famila Dwi Winati","score":216,"position":4}],"rank":{"2016-48":[{"playerID":"276413484","name":"Astri Winati","score":540,"position":1},{"playerID":"259002958","name":"Iklas SIG","score":351,"position":2},{"playerID":"269902468","name":"Nimah Eka Winati","score":348,"position":3},{"playerID":"192239640","name":"Famila Dwi Winati","score":216,"position":4}]}}
