{"chanID":"-166618818","lastUpdated":"2016-12-07T05:00:11Z","total":[{"playerID":"275725283","name":"Regina Riantoni","score":8480,"position":1},{"playerID":"268100176","name":"Christy Jenner","score":7279,"position":2},{"playerID":"297739994","name":"Michelle Karta","score":5989,"position":3},{"playerID":"247111113","name":"Jessica Angelina W","score":4553,"position":4},{"playerID":"298836355","name":"Daniel Fernanda","score":3144,"position":5},{"playerID":"253820833","name":"Christopher Owen","score":2125,"position":6},{"playerID":"264050917","name":"monica kurniawan","score":1913,"position":7},{"playerID":"257474280","name":"felicia aurelia","score":1367,"position":8},{"playerID":"253624013","name":"Ariel Patrick R","score":1084,"position":9},{"playerID":"298182376","name":"Steven Kent","score":818,"position":10},{"playerID":"267515135","name":"Agustinus Tobias","score":800,"position":11},{"playerID":"275502341","name":"natasya sherly","score":618,"position":12},{"playerID":"229389892","name":"Aldrich Valerian","score":572,"position":13},{"playerID":"299720594","name":"Nael","score":108,"position":14},{"playerID":"241409367","name":"Нафанаил  DJ","score":81,"position":15},{"playerID":"296437112","name":"Alfons Aditya","score":71,"position":16},{"playerID":"249603787","name":"Chandra Wahyudi","score":57,"position":17},{"playerID":"199629552","name":"Emmanuela Stefany","score":12,"position":18},{"playerID":"284150040","name":"Brigitta Isabella","score":11,"position":19}],"rank":{"2016-48":[{"playerID":"275725283","name":"Regina Riantoni","score":8394,"position":1},{"playerID":"268100176","name":"Christy Jenner","score":7252,"position":2},{"playerID":"297739994","name":"Michelle Karta","score":5930,"position":3},{"playerID":"247111113","name":"Jessica Angelina W","score":4553,"position":4},{"playerID":"298836355","name":"Daniel Fernanda","score":3144,"position":5},{"playerID":"253820833","name":"Christopher Owen","score":2103,"position":6},{"playerID":"264050917","name":"monica kurniawan","score":1913,"position":7},{"playerID":"257474280","name":"felicia aurelia","score":1367,"position":8},{"playerID":"253624013","name":"Ariel Patrick R","score":1079,"position":9},{"playerID":"298182376","name":"Steven Kent","score":818,"position":10},{"playerID":"267515135","name":"Agustinus Tobias","score":800,"position":11},{"playerID":"275502341","name":"natasya sherly","score":618,"position":12},{"playerID":"229389892","name":"Aldrich Valerian","score":572,"position":13},{"playerID":"241409367","name":"Нафанаил  DJ","score":81,"position":14},{"playerID":"296437112","name":"Alfons Aditya","score":71,"position":15},{"playerID":"299720594","name":"Nael","score":68,"position":16},{"playerID":"249603787","name":"Chandra Wahyudi","score":57,"position":17},{"playerID":"199629552","name":"Emmanuela Stefany","score":12,"position":18},{"playerID":"284150040","name":"Brigitta Isabella","score":11,"position":19}],"2016-49":[{"playerID":"275725283","name":"Regina Riantoni","score":86,"position":1},{"playerID":"297739994","name":"Michelle Karta","score":59,"position":2},{"playerID":"299720594","name":"Nael","score":40,"position":3},{"playerID":"268100176","name":"Christy Jenner","score":27,"position":4},{"playerID":"253820833","name":"Christopher Owen","score":22,"position":5},{"playerID":"253624013","name":"Ariel Patrick R","score":5,"position":6}]}}
