{"chanID":"-166678307","lastUpdated":"2016-12-15T05:00:12Z","total":[{"playerID":"246070248","name":"Cakrawidia Stuti","score":3278,"position":1},{"playerID":"272579074","name":"Wana Edys","score":2416,"position":2},{"playerID":"226549129","name":"Sukarta JL","score":2383,"position":3},{"playerID":"244023377","name":"Toni Harwan","score":2027,"position":4},{"playerID":"175436769","name":"Arif Z - KP Palopo 91900","score":646,"position":5},{"playerID":"243727887","name":"Faisal Achyar75","score":611,"position":6},{"playerID":"294441431","name":"Nanda Madong","score":289,"position":7}],"rank":{"2016-48":[{"playerID":"246070248","name":"Cakrawidia Stuti","score":3006,"position":1},{"playerID":"272579074","name":"Wana Edys","score":2416,"position":2},{"playerID":"226549129","name":"Sukarta JL","score":2264,"position":3},{"playerID":"244023377","name":"Toni Harwan","score":1888,"position":4},{"playerID":"175436769","name":"Arif Z - KP Palopo 91900","score":646,"position":5},{"playerID":"243727887","name":"Faisal Achyar75","score":611,"position":6},{"playerID":"294441431","name":"Nanda Madong","score":289,"position":7}],"2016-50":[{"playerID":"246070248","name":"Cakrawidia Stuti","score":272,"position":1},{"playerID":"244023377","name":"Toni Harwan","score":139,"position":2},{"playerID":"226549129","name":"Sukarta JL","score":119,"position":3}]}}
