{"chanID":"-171571504","lastUpdated":"2016-12-03T22:46:22Z","total":[{"playerID":"288607694","name":"Fhu harlotte","score":1864,"position":1},{"playerID":"231062669","name":"Christian Sanjaya","score":1789,"position":2},{"playerID":"276272996","name":"Billa Soputan","score":1198,"position":3},{"playerID":"240029214","name":"pian takur99","score":1002,"position":4},{"playerID":"297596235","name":"Abdul Tramposo 4931","score":802,"position":5},{"playerID":"298715319","name":"u h a r a T","score":483,"position":6},{"playerID":"282468218","name":"666 luna","score":434,"position":7},{"playerID":"283875140","name":"Andre Juntak","score":324,"position":8},{"playerID":"296403372","name":"Bajing Keselek","score":256,"position":9},{"playerID":"236907654","name":"Lutfi Ardiansyah","score":6,"position":10}],"rank":{"2016-41":[{"playerID":"282468218","name":"666 luna","score":217,"position":1},{"playerID":"288607694","name":"Fhuu -sama","score":182,"position":2},{"playerID":"276272996","name":"Billa Soputan","score":169,"position":3},{"playerID":"296403372","name":"Bajing Keselek","score":128,"position":4},{"playerID":"297596235","name":"Abdul Tramposo 4931","score":37,"position":5},{"playerID":"298715319","name":"Azhar Rasyid","score":9,"position":6}],"2016-42":[{"playerID":"282468218","name":"666 luna","score":217,"position":1},{"playerID":"288607694","name":"Fhuu -sama","score":182,"position":2},{"playerID":"276272996","name":"Billa Soputan","score":169,"position":3},{"playerID":"296403372","name":"Bajing Keselek","score":128,"position":4},{"playerID":"297596235","name":"Abdul Tramposo 4931","score":37,"position":5},{"playerID":"298715319","name":"Azhar Rasyid","score":9,"position":6}],"2016-48":[{"playerID":"231062669","name":"Christian Sanjaya","score":1789,"position":1},{"playerID":"288607694","name":"Fhu harlotte","score":1500,"position":2},{"playerID":"240029214","name":"pian takur99","score":1002,"position":3},{"playerID":"276272996","name":"Billa Soputan","score":860,"position":4},{"playerID":"297596235","name":"Abdul Tramposo 4931","score":728,"position":5},{"playerID":"298715319","name":"u h a r a T","score":465,"position":6},{"playerID":"283875140","name":"Andre Juntak","score":324,"position":7},{"playerID":"236907654","name":"Lutfi Ardiansyah","score":6,"position":8}]}}
