{"chanID":"-172889807","lastUpdated":"2016-12-03T22:46:22Z","total":[{"playerID":"286573986","name":"Aidil Piper","score":256,"position":1},{"playerID":"240694570","name":"David ..","score":148,"position":2},{"playerID":"247458719","name":"Toni Buaton","score":62,"position":3}],"rank":{"2016-48":[{"playerID":"286573986","name":"Aidil Piper","score":256,"position":1},{"playerID":"240694570","name":"David ..","score":148,"position":2},{"playerID":"247458719","name":"Toni Buaton","score":62,"position":3}]}}
