{"chanID":"-174127733","lastUpdated":"2016-12-01T05:00:15+01:00","total":[{"playerID":"258223322","name":"Fellyza Sanjaya","score":476,"position":1},{"playerID":"206492816","name":"Ilinne Yuvita","score":373,"position":2},{"playerID":"323212268","name":"Dea Hanna","score":175,"position":3},{"playerID":"309202160","name":"Gen","score":98,"position":4},{"playerID":"185888735","name":"Antonius Abednego","score":94,"position":5}],"rank":{"2016-48":[{"playerID":"258223322","name":"Fellyza Sanjaya","score":476,"position":1},{"playerID":"206492816","name":"Ilinne Yuvita","score":373,"position":2},{"playerID":"323212268","name":"Dea Hanna","score":175,"position":3},{"playerID":"309202160","name":"Gen","score":98,"position":4},{"playerID":"185888735","name":"Antonius Abednego","score":94,"position":5}]}}
