{"chanID":"-175581711","lastUpdated":"2016-12-08T05:00:11Z","total":[{"playerID":"259875670","name":"Balqis Salsabila Syani","score":185,"position":1},{"playerID":"221442031","name":"Larasati","score":102,"position":2},{"playerID":"290933559","name":"Mayafbt","score":88,"position":3}],"rank":{"2016-49":[{"playerID":"259875670","name":"Balqis Salsabila Syani","score":185,"position":1},{"playerID":"221442031","name":"Larasati","score":102,"position":2},{"playerID":"290933559","name":"Mayafbt","score":88,"position":3}]}}
