{"chanID":"-176839878","lastUpdated":"2016-12-03T22:46:22Z","total":[{"playerID":"296521634","name":"Rahmat Saiful","score":549,"position":1},{"playerID":"277023141","name":"Asrullah Syahrir","score":433,"position":2},{"playerID":"179601440","name":"Yulianti ismayana","score":40,"position":3}],"rank":{"2016-48":[{"playerID":"296521634","name":"Rahmat Saiful","score":549,"position":1},{"playerID":"277023141","name":"Asrullah Syahrir","score":433,"position":2},{"playerID":"179601440","name":"Yulianti ismayana","score":40,"position":3}]}}
