{"chanID":"-176021987","lastUpdated":"2016-12-03T22:46:22Z","total":[{"playerID":"298586758","name":"Indah Ariska","score":613,"position":1},{"playerID":"281216680","name":"Rica Lucya Faninta","score":284,"position":2},{"playerID":"276083115","name":"Sarah Permata Sari","score":153,"position":3},{"playerID":"294492891","name":"Arie Hardiansyah","score":108,"position":4}],"rank":{"2016-48":[{"playerID":"298586758","name":"Indah Ariska","score":613,"position":1},{"playerID":"281216680","name":"Rica Lucya Faninta","score":284,"position":2},{"playerID":"276083115","name":"Sarah Permata Sari","score":153,"position":3},{"playerID":"294492891","name":"Arie Hardiansyah","score":108,"position":4}]}}
