{"chanID":"-177828307","lastUpdated":"2016-12-15T05:00:12Z","total":[{"playerID":"294480565","name":"SRubayah W","score":574,"position":1},{"playerID":"201317082","name":"Gamas","score":380,"position":2},{"playerID":"269035031","name":"LN Putri","score":345,"position":3},{"playerID":"118102892","name":"Ariska Winda Sari","score":177,"position":4},{"playerID":"316363285","name":"Ferry Firmansyah","score":108,"position":5}],"rank":{"2016-50":[{"playerID":"294480565","name":"SRubayah W","score":574,"position":1},{"playerID":"201317082","name":"Gamas","score":380,"position":2},{"playerID":"269035031","name":"LN Putri","score":345,"position":3},{"playerID":"118102892","name":"Ariska Winda Sari","score":177,"position":4},{"playerID":"316363285","name":"Ferry Firmansyah","score":108,"position":5}]}}
