{"chanID":"-180957524","lastUpdated":"2017-01-01T23:55:11Z","total":[{"playerID":"250447846","name":"Nopiya","score":433,"position":1},{"playerID":"308155571","name":"Asep Zaenal","score":331,"position":2},{"playerID":"325666094","name":"Desya Aisyah","score":57,"position":3}],"rank":{"2016-52":[{"playerID":"250447846","name":"Nopiya","score":433,"position":1},{"playerID":"308155571","name":"Asep Zaenal","score":331,"position":2},{"playerID":"325666094","name":"Desya Aisyah","score":57,"position":3}]}}
