{"chanID":"-183222054","lastUpdated":"2016-12-03T22:46:22Z","total":[{"playerID":"218317982","name":"Dimas Razaqa","score":2568,"position":1},{"playerID":"249765020","name":"Herawati Salsabila","score":2359,"position":2},{"playerID":"310935743","name":"ajar awaniac","score":1535,"position":3},{"playerID":"245787894","name":"Arif Trip","score":493,"position":4},{"playerID":"255050797","name":"Nindya deva chandra","score":261,"position":5}],"rank":{"2016-48":[{"playerID":"218317982","name":"Dimas Razaqa","score":2568,"position":1},{"playerID":"249765020","name":"Herawati Salsabila","score":2359,"position":2},{"playerID":"310935743","name":"ajar awaniac","score":1535,"position":3},{"playerID":"245787894","name":"Arif Trip","score":493,"position":4},{"playerID":"255050797","name":"Nindya deva chandra","score":261,"position":5}]}}
