{"chanID":"-185692366","lastUpdated":"2017-01-01T05:00:11Z","total":[{"playerID":"252889620","name":"Ardhi","score":11368,"position":1},{"playerID":"320475437","name":"Thomas KEBROK","score":7765,"position":2},{"playerID":"269985187","name":"Alexius Dibitianto","score":3318,"position":3},{"playerID":"140848391","name":"Fide P","score":3033,"position":4},{"playerID":"197550985","name":"Ardiyan Wisnu","score":2472,"position":5}],"rank":{"2016-51":[{"playerID":"252889620","name":"Ardhi","score":5137,"position":1},{"playerID":"320475437","name":"Thomas KEBROK","score":3460,"position":2},{"playerID":"140848391","name":"Fide P","score":1478,"position":3},{"playerID":"269985187","name":"Alexius Dibitianto","score":1316,"position":4},{"playerID":"197550985","name":"Ardiyan Wisnu","score":1236,"position":5}],"2016-52":[{"playerID":"252889620","name":"Ardhi","score":6231,"position":1},{"playerID":"320475437","name":"Thomas KEBROK","score":4305,"position":2},{"playerID":"269985187","name":"Alexius Dibitianto","score":2002,"position":3},{"playerID":"140848391","name":"Fide P","score":1555,"position":4},{"playerID":"197550985","name":"Ardiyan Wisnu","score":1236,"position":5}]}}
