{"chanID":"-190045578","lastUpdated":"2017-01-01T05:00:11Z","total":[{"playerID":"327968004","name":"Fatimah Karimah","score":1325,"position":1},{"playerID":"323527085","name":"Zeen Alaydrus","score":782,"position":2},{"playerID":"304151352","name":"Zahra","score":474,"position":3},{"playerID":"300692119","name":"Alwi Alaydrus","score":443,"position":4},{"playerID":"307204922","name":"Muhammad Zen","score":296,"position":5}],"rank":{"2016-50":[{"playerID":"327968004","name":"Fatimah Karimah","score":113,"position":1},{"playerID":"304151352","name":"Zahra","score":56,"position":2},{"playerID":"300692119","name":"Alwi Alaydrus","score":43,"position":3}],"2016-51":[{"playerID":"327968004","name":"Fatimah Karimah","score":606,"position":1},{"playerID":"323527085","name":"Zeen Alaydrus","score":391,"position":2},{"playerID":"304151352","name":"Zahra","score":209,"position":3},{"playerID":"300692119","name":"Alwi Alaydrus","score":200,"position":4},{"playerID":"307204922","name":"Muhammad Zen","score":148,"position":5}],"2016-52":[{"playerID":"327968004","name":"Fatimah Karimah","score":606,"position":1},{"playerID":"323527085","name":"Zeen Alaydrus","score":391,"position":2},{"playerID":"304151352","name":"Zahra","score":209,"position":3},{"playerID":"300692119","name":"Alwi Alaydrus","score":200,"position":4},{"playerID":"307204922","name":"Muhammad Zen","score":148,"position":5}]}}
