{"chanID":"-193549900","lastUpdated":"2016-12-03T22:46:22Z","total":[{"playerID":"279074116","name":"John Alfajry","score":232,"position":1},{"playerID":"233946141","name":"Mochamad Ridwan","score":210,"position":2},{"playerID":"308492815","name":"Ivan Rama A","score":33,"position":3}],"rank":{"2016-48":[{"playerID":"279074116","name":"John Alfajry","score":232,"position":1},{"playerID":"233946141","name":"Mochamad Ridwan","score":210,"position":2},{"playerID":"308492815","name":"Ivan Rama A","score":33,"position":3}]}}
