{"chanID":"-194417348","lastUpdated":"2016-12-08T05:00:11Z","total":[{"playerID":"318348108","name":"M. Shandy Putra","score":2318,"position":1},{"playerID":"323885482","name":"Deby Ariyandi","score":2129,"position":2},{"playerID":"256263557","name":"Muhaqiqin","score":1096,"position":3}],"rank":{"2016-49":[{"playerID":"318348108","name":"M. Shandy Putra","score":2318,"position":1},{"playerID":"323885482","name":"Deby Ariyandi","score":2129,"position":2},{"playerID":"256263557","name":"Muhaqiqin","score":1096,"position":3}]}}
